{
	"schemaVersion": 1,
	"id": "photophobia",
	"version": "${version}",
	"name": "畏光",
	"description": "你会在黑夜里点亮第一排灯塔吗？",
	"authors": [
		"Zhonz",
		"BrokenSnake"
	],
	"contact": {
		"homepage": "https://github.com/Zhonz/Photophobia",
		"sources": "https://github.com/Zhonz/Photophobia"
	},
	"license": "CC0-1.0",
	"icon": "assets/photophobia/icon.png",
	"environment": "*",
	"entrypoints": {
		"main": [
			"com.zzandbrokensnake.photophobia.PhotophobiaMod"
		],
		"client": [
			"com.zzandbrokensnake.photophobia.PhotophobiaModClient"
		]
	},
	"mixins": [
		"photophobia.mixins.json",
		{
			"config": "photophobia.client.mixins.json",
			"environment": "client"
		}
	],
  "depends": {
    "fabricloader": ">=0.17.3",
    "minecraft": "~1.20.1",
    "java": ">=17",
    "fabric-api": "*"
  },
	"suggests": {
		"modmenu": "*"
	},
	"custom": {
		"modmenu": {
			"links": {
				"modmenu.github": "https://github.com/Zhonz/Photophobia",
				"modmenu.discord": "https://discord.gg/example"
			},
			"badges": [],
			"update_checker": true
		}
	}
}
